{
    "X": [
        [
            31,
            64,
            18,
            13,
            4,
            8,
            16,
            4
        ],
        [
            15,
            57,
            21,
            13,
            1,
            10,
            19,
            9
        ],
        [
            32,
            63,
            26,
            16,
            4,
            4,
            15,
            2
        ],
        [
            17,
            62,
            29,
            15,
            1,
            14,
            12,
            9
        ],
        [
            18,
            35,
            19,
            11,
            1,
            4,
            9,
            6
        ]
    ],
    "W": [
        [
            2,
            8,
            59,
            22,
            15,
            9,
            16,
            27
        ],
        [
            5,
            16,
            21,
            7,
            43,
            35,
            12,
            7
        ],
        [
            1,
            51,
            14,
            0,
            3,
            52,
            41,
            0
        ],
        [
            6,
            3,
            1,
            25,
            85,
            38,
            1,
            0
        ],
        [
            7,
            3,
            8,
            67,
            11,
            4,
            3,
            0
        ]
    ],
    "cond_prob": [
        [
            [
                0.19620253165,
                0.050632911392,
                0.14482758621,
                0.062068965517,
                0.024691358025,
                0.38993710692,
                0.075471698113,
                0.1067961165
            ]
        ],
        [
            [
                0.40506329114,
                0.10126582278,
                0.089655172414,
                0.1975308642,
                0.024691358025,
                0.18238993711,
                0.056603773585,
                0.0097087378641
            ]
        ],
        [
            [
                0.11392405063,
                0.025316455696,
                0.0068965517241,
                0.38888888889,
                0.092592592593,
                0.094339622642,
                0.17475728155,
                0.038834951456
            ]
        ],
        [
            [
                0.082278481013,
                0.10344827586,
                0.068965517241,
                0.16049382716,
                0.012345679012,
                0.0062893081761,
                0.33980582524,
                0.087378640777
            ]
        ],
        [
            [
                0.025316455696,
                0.39310344828,
                0.13103448276,
                0.098765432099,
                0.10691823899,
                0.088050314465,
                0.18446601942,
                0.058252427184
            ]
        ]
    ],
    "W_agg": [
        [
            158
        ],
        [
            146
        ],
        [
            162
        ],
        [
            159
        ],
        [
            103
        ]
    ],
    "group_agg": 8,
    "prob": [
        [
            0.1553618795,
            0.38652898825,
            0.15541871921,
            0.093529746116,
            0.015119363395,
            0.055039787798,
            0.097707464949,
            0.041294050777
        ]
    ],
    "iterations": 1,
    "logLik": -86.9890281934,
    "time": 5e-06,
    "message": "Converged",
    "status": 0,
    "sd": [
        [
            0.021023571113,
            0.0080189210921,
            0.012300128923,
            0.0033072343738,
            0.0042520817142,
            0.010802335783,
            0.0079828847779,
            0.0093543304608
        ]
    ],
    "method": "mult",
    "ll_threshold": "-Inf",
    "param_threshold": 0.0001,
    "maxtime": 3600,
    "maxiter": 1000,
    "initial_prob": "group_proportional",
    "ballotbox_id": [
        "1",
        "2",
        "3",
        "4",
        "5"
    ],
    "candidates_id": [
        "C1",
        "C2",
        "C3",
        "C4",
        "C5",
        "C6",
        "C7",
        "C8"
    ],
    "group_id": [
        "X18.19",
        "X20.29",
        "X30.39",
        "X40.49",
        "X50.59",
        "X60.69",
        "X70.79",
        "X80."
    ],
    "p_values": [
        0.536,
        0.418,
        0.188,
        0.284,
        0.883
    ],
    "p_values_trials": [
        3,
        3,
        3,
        3,
        3
    ]
}