{
    "X": [
        [
            15,
            44,
            47,
            29,
            1,
            2,
            9,
            4
        ],
        [
            14,
            15,
            9,
            9,
            0,
            1,
            8,
            0
        ]
    ],
    "W": [
        [
            2,
            14,
            13,
            12,
            45,
            35,
            21,
            9
        ],
        [
            1,
            5,
            7,
            19,
            9,
            8,
            7,
            0
        ]
    ],
    "W_agg": [
        [
            151
        ],
        [
            56
        ]
    ],
    "group_agg": 8,
    "method": "mult",
    "cond_prob": [
        [
            [
                0.099337748344,
                0.31125827815,
                0.0066225165563,
                0.059602649007,
                0.25,
                0.16071428571,
                0,
                0.14285714286
            ]
        ],
        [
            [
                0.29139072848,
                0.19205298013,
                0.013245033113,
                0.026490066225,
                0.26785714286,
                0.16071428571,
                0.017857142857,
                0
            ]
        ]
    ],
    "prob": [
        [
            0.14009661836,
            0.28502415459,
            0.27053140097,
            0.18357487923,
            0.0048309178744,
            0.014492753623,
            0.082125603865,
            0.019323671498
        ]
    ],
    "iterations": 1,
    "logLik": -29.8507922684,
    "time": 7e-06,
    "message": "Converged",
    "status": 0,
    "maxiter": 3600,
    "param_threshold": 0.0001,
    "ll_threshold": "-Inf",
    "initial_prob": "group_proportional",
    "ballotbox_id": [
        "1M-2M-1V",
        "2V"
    ],
    "candidates_id": [
        "C1",
        "C2",
        "C3",
        "C4",
        "C5",
        "C6",
        "C7",
        "C8"
    ],
    "group_id": [
        "X18.19",
        "X20.29",
        "X30.39",
        "X40.49",
        "X50.59",
        "X60.69",
        "X70.79",
        "X80."
    ],
    "p_values": [
        0.635,
        0.133
    ],
    "p_values_trials": [
        3,
        3
    ]
}